otp_twilio/__init__.py
otp_twilio/admin.py
otp_twilio/apps.py
otp_twilio/conf.py
otp_twilio/models.py
otp_twilio/tests.py
otp_twilio/migrations/0001_initial.py
otp_twilio/migrations/0002_last_t.py
otp_twilio/migrations/0003_longer_number.py
otp_twilio/migrations/0004_sidechanneldevice.py
otp_twilio/migrations/__init__.py
django_otp_twilio-1.0.4.dist-info/METADATA
django_otp_twilio-1.0.4.dist-info/WHEEL
django_otp_twilio-1.0.4.dist-info/licenses/LICENSE
django_otp_twilio-1.0.4.dist-info/RECORD
