Metadata-Version: 2.1
Name: django-otp-twilio
Version: 1.0.4
Summary: A django-otp plugin that delivers tokens via Twilio's SMS service.
Project-URL: Homepage, https://github.com/django-otp/django-otp-twilio
Project-URL: Documentation, https://django-otp-twilio.readthedocs.io/
Author-email: Peter Sagerson <psagers@ignorare.net>
License-Expression: Unlicense
License-File: LICENSE
Classifier: Development Status :: 5 - Production/Stable
Classifier: Framework :: Django
Classifier: Intended Audience :: Developers
Classifier: License :: OSI Approved :: The Unlicense (Unlicense)
Classifier: Programming Language :: Python :: 3
Classifier: Programming Language :: Python :: 3 :: Only
Classifier: Topic :: Security
Classifier: Topic :: Software Development :: Libraries :: Python Modules
Requires-Python: >=3.7
Requires-Dist: django-otp~=1.0
Requires-Dist: requests
